mediainline/__init__.py
mediainline/custom_exception.py
mediainline/logger.py
mediainline/website.py
mediainline/youtube.py
mediainline-0.0.2.dist-info/LICENSE
mediainline-0.0.2.dist-info/METADATA
mediainline-0.0.2.dist-info/WHEEL
mediainline-0.0.2.dist-info/top_level.txt
mediainline-0.0.2.dist-info/RECORD
