Metadata-Version: 2.1
Name: mediainline
Version: 0.0.2
Summary: A small python package
Home-page: https://github.com/apurbo04/mediainline-PyPi-packages
Author: apurbo04
Author-email: apurbasharma23@gmail.com
License: MIT
Project-URL: Bug Tracker, https://github.com/apurbo04/mediainline-PyPi-packages/issues
Classifier: Programming Language :: Python :: 3.8
Classifier: Programming Language :: Python :: 3.9
Classifier: Operating System :: OS Independent
Requires-Python: >=3.8
License-File: LICENSE
Requires-Dist: ensure==1.0.2
Requires-Dist: py-youtube==1.1.7
Provides-Extra: testing
Requires-Dist: pytest>=7.1.3; extra == "testing"
Requires-Dist: mypy>=0.971; extra == "testing"
Requires-Dist: flake8>=5.0.4; extra == "testing"
Requires-Dist: tox>=3.25.1; extra == "testing"
